Workbook

Sheet Roadmap
A1: Lot | B1: Feature | C1: Description | D1: Critères d'évaluation | E1: Dépendances | F1: Durée (j) | G1: Deadline | H1: Notes
A2: LOT 0 — FONDATIONS
A3: Lot 0 | B3: Création tickets backlog Lot 0 | C3: Découpage du Lot 0 en tickets détaillés avant le début du développement. | D3: - Tous les items du lot sont tracés en tickets - Critères d'acceptance rédigés - Prêts à être pris en sprint | E3: — | F3: 1 | G3: 05/06/2026 | H3: Règle : 1j en début de chaque lot
A4: Lot 0 | B4: Setup projet Symfony 7 + Docker Swarm | C4: Initialisation du projet Symfony 7 from scratch. Reprise de la stack Docker Swarm du Tage blanc (éprouvée sur charge). Configuration des volumes persistants, réseaux, secrets, déploiement Scaleway. | D4: - Projet Symfony 7 fonctionnel en local via docker-compose - Déploiement Scaleway via Docker Swarm - Volumes persistants OK - Healthchecks configurés | E4: — | F4: 2 | G4: 05/06/2026 | H4: Reprise stack Tage blanc
A5: Lot 0 | B5: GitLab Runner + pipelines CI/CD | C5: Pipelines build / test / deploy staging + prod. Cache composer et yarn. Déploiement automatique sur push main/staging. | D5: - Push main = déploiement prod - Push staging = déploiement staging - Cache composer/yarn actif - Tests lancés automatiquement | E5: Setup projet | F5: 2 | G5: 05/06/2026
A6: Lot 0 | B6: Schema BDD complet + migrations + seeders | C6: Design du schéma complet (~30 tables). Migrations Doctrine, index, contraintes FK. Seeders dev pour test. | D6: - ~30 tables créées via migrations - Relations et index en place - Seeders dev opérationnels - Doctrine génère le schéma sans erreur | E6: Setup projet | F6: 1.5 | G6: 05/06/2026
A7: Lot 0 | B7: Intégration Mux | C7: Signed playback tokens, upload direct depuis l'admin, webhooks asset ready. Gestion des IDs (asset_id, playback_id, upload_id). | D7: - Upload direct admin fonctionnel - Signed playback sur le front - Webhook asset.ready traité | E7: Schema BDD | F7: 0.5 | G7: 05/06/2026
A8: Lot 0 | B8: Sentry monitoring | C8: Installation bundle Sentry, configuration DSN, projet dédié V3, intégration exceptions handlers, traces de performance. | D8: - Erreurs remontent dans Sentry - Projet V3 dédié - Trace performance sur routes principales | E8: Setup projet | F8: 0.5 | G8: 05/06/2026
A9: Lot 0 | B9: Auth complète | C9: Inscription + vérification email (VerifyEmailBundle), login/logout, remember me 1 an via CacheRememberMeTokenProvider, reset password, session token unique (anti multi-connexions), firewall Symfony Security, voters. | D9: - Inscription + vérif email OK - Login/logout fonctionnel - Remember me 1 an actif - Reset password opérationnel - Session token unique empêche multi-connexions | E9: Schema BDD | F9: 2 | G9: 05/06/2026
A10: Lot 0 | B10: Modèle de données abonnement + codes promo | C10: Entités Doctrine (Subscription, PromoCode, SubscriptionHistory) avec états (active, paused, expired, canceled). Codes promo : type fixed/percentage, conditions de validité, compteur usage, création/gestion admin. Application au checkout Stripe avec traçage. | D10: - Entités créées avec transitions d'état - Codes promo admin CRUD complet - Application checkout Stripe tracée - Historique consolidé | E10: Schema BDD | F10: 2 | G10: 05/06/2026 | H10: Repensé vs V1
A11: Lot 0 | B11: Anti-chevauchement d'abonnements | C11: Un seul abo écrit actif à la fois, un seul oral, un seul dossier. Validation à la souscription (checkout Stripe), blocage avec message clair si conflit. Cas edge : renouvellement anticipé, upgrade mid-période. | D11: - Validation bloque souscription si conflit - Message clair user - Cas renouvellement/upgrade gérés | E11: Modèle abo | F11: 1 | G11: 05/06/2026
A12: Lot 0 | B12: Upgrade / downgrade / pause / reprise | C12: Transitions d'état cohérentes, gestion du prorata via Stripe, conservation de l'historique. UX user minimaliste (page paramètres → bouton). | D12: - Upgrade/downgrade avec prorata Stripe - Pause/reprise fonctionnelle - Historique conservé | E12: Anti-chevauchement | F12: 0.5 | G12: 05/06/2026
A13: Lot 0 | B13: CRUD users + reset password + alertes admin | C13: Liste paginée + recherche, édition profil, reset password avec génération + email, alertes (multi-connexions, discount_counter > 80, export CSV connexions). | D13: - Liste paginée fonctionnelle - Reset password avec email - Alertes multi-connexions remontées - Export CSV disponible | E13: Auth | F13: 0.25 | G13: 05/06/2026 | H13: CRUD simple
A14: Lot 0 | B14: CRUD catégories + sous-catégories | C14: Les 6 sections du TageMage + section Stratégie. Reorder, visibilité, thematic slug. Sous-catégories rattachées. | D14: - 6 sections + Stratégie créées - Reorder fonctionnel - Slugs uniques | E14: Schema BDD | F14: 0.25 | G14: 05/06/2026 | H14: CRUD simple
A15: Lot 0 | B15: CRUD cours avec CKEditor + upload Mux | C15: Titre, contenu CKEditor, vidéo Mux via upload direct, difficulté, visibilité publique, rattachement catégorie/sous-catégorie. Reorder par position. | D15: - Création cours avec vidéo uploadée sur Mux - CKEditor fonctionnel - Reorder par position - Rattachement catégories | E15: Mux + CRUD catégories | F15: 0.5 | G15: 05/06/2026 | H15: CRUD simple
A16: Lot 0 | B16: CRUD exercices + reorder drag&drop | C16: Liste filtrée par catégorie, drag&drop de l'ordre, rattachement cours/catégorie, type (tagemage_type ou cours). | D16: - Liste filtrée par catégorie - Drag&drop opérationnel - Types distincts | E16: CRUD catégories | F16: 0.25 | G16: 05/06/2026 | H16: CRUD simple
A17: Lot 0 | B17: CRUD questions d'exercice | C17: 5 réponses + bonne réponse, titre public, titre interne, correction texte + vidéo Mux liée, flag thème (micro-compétence), flag difficulté. | D17: - 5 réponses + bonne réponse OK - Correction texte + vidéo - Flag thème et difficulté | E17: CRUD exercices + Mux | F17: 0.25 | G17: 05/06/2026 | H17: CRUD simple
A18: Lot 0 | B18: CRUD TageMage + questions | C18: TageMage blanc (classique ou mensuel), liste de questions rattachées, type de sous-test, ordre. | D18: - TageMage classique et mensuel - Questions rattachées par type de sous-test - Ordre défini | E18: CRUD questions | F18: 0.5 | G18: 05/06/2026
A19: Lot 0 | B19: CRUD parcours + parties + items pondérés | C19: Structure hiérarchique (Parcours → Parts → Items), poids horaire sur chaque item, liens vers cours/exos/TageMage/flashcards/calcul/lecture, duplication de parcours. Les 15 profils par tranche de 25 points. | D19: - Parcours → parts → items créable - Poids horaire par item - Duplication fonctionnelle - Liens vers tous types d'items | E19: CRUD cours+exos+TageMage+flashcards | F19: 0.5 | G19: 05/06/2026
A20: Lot 0 | B20: CRUD flashcards + groupes | C20: Groupes thématiques, cartes recto/verso, image optionnelle, rattachement sous-catégorie. | D20: - Groupes thématiques créables - Recto/verso + image - Rattachement sous-catégorie | E20: CRUD catégories | F20: 0.25 | G20: 05/06/2026 | H20: CRUD simple
A21: Lot 0 | B21: CRUD micro-compétences + drills + test positionnement | C21: 3 entités liées. Micro-compétences rattachées aux leçons. Drills (5 questions par leçon). Test de positionnement (12-15 questions avec mapping score → niveau). | D21: - Micro-compétences rattachées aux leçons - Drills 5 Q par leçon - Test positionnement fonctionnel | E21: CRUD cours | F21: 0.75 | G21: 05/06/2026
A22: Lot 0 | B22: Étude migration | C22: Audit du schéma actuel. Livrable : note de décision 'on migre / on ne migre pas / partiellement' par entité (users, cours, exos, questions, erreurs, parcours, abos). Dry run sur échantillon 100 users + 200 exos. | D22: - Note de décision livrée - Dry run testé sur échantillon - Plan de migration par entité | E22: Schema BDD | F22: 2 | G22: 05/06/2026 | H22: Conditionne le Lot 6
A23: Lot 0 | B23: Recette fin de Lot 0 | C23: Tests E2E : inscription/auth, admin fonctionnel sur tous les CRUDs, Grégoire peut saisir 1 cours + 1 exo + 1 TageMage en conditions réelles. Corrections critiques. | D23: - Inscription + auth OK - Tous les CRUDs admin testés - Saisie contenu réelle validée par Grégoire - 0 anomalie critique | E23: Tous items Lot 0 | F23: 1 | G23: 05/06/2026
A24: Total lot 0 | C24: =SUM(F2:F23) -> 19.5
A25: LOT 1 — MONÉTISATION & ENTRÉE
A26: Lot 1 | B26: Création tickets backlog Lot 1 | C26: Découpage du Lot 1 en tickets détaillés avant le début du développement. | D26: - Tous les items du lot sont tracés en tickets - Critères d'acceptance rédigés | E26: Fin Lot 0 | F26: 1 | G26: 19/06/2026
A27: Lot 1 | B27: Onboarding pré-paiement multi-étapes | C27: Flux en 4 étapes : email+mdp, prénom+nom, école visée + date passage TM + niveau auto-évalué + heures dispo, récap. Barre de progression, validations, responsive, redirection paywall. | D27: - 4 étapes fonctionnelles - Barre de progression - Validations email et date - Responsive - Redirection paywall en fin | E27: Auth | F27: 0.5 | G27: 19/06/2026
A28: Lot 1 | B28: Témoignages page de paiement | C28: Intégration témoignages sur la page pricing + checkout Stripe, en rotation. Simple affichage. | D28: - Témoignages affichés en rotation - Présents sur pricing ET checkout | E28: Onboarding pré-paiement | F28: 0.25 | G28: 19/06/2026
A29: Lot 1 | B29: Plans Stripe + checkout + webhooks | C29: Page pricing avec 3 plans (Flex 87€, Optimal 219€, Premium). Checkout Stripe, succès et cancel URLs. Webhooks : invoice.payment_succeeded, customer.subscription.deleted, idempotence. Branché sur système abo Lot 0. | D29: - 3 plans affichés - Checkout Stripe fonctionnel - Webhooks idempotents - Abonnement activé après paiement | E29: Modèle abo | F29: 1 | G29: 19/06/2026
A30: Lot 1 | B30: Onboarding post-paiement | C30: Vidéo bienvenue formateurs, test positionnement (12-15 questions, 3 par domaine, scores affichés, sauvegarde), écran CTA Discord avec lien externe, premier exercice 5 questions selon faiblesses, correction placeholder, redirection dashboard. | D30: - Vidéo bienvenue affichée - Test positionnement 12-15 Q - Scores par domaine sauvegardés - CTA Discord - Premier exo généré | E30: Checkout + CRUD test positionnement | F30: 1 | G30: 19/06/2026
A31: Lot 1 | B31: Freemium avec cadenas conditionnels | C31: User non-abonné = 1 cours / 1 exo / 1 TageMage gratuits identifiés en admin. Cadenas visuel sur tous les autres contenus, clic → redirection paywall. Twig helper réutilisable. | D31: - 1 cours/1 exo/1 TM gratuits accessibles - Cadenas sur autres contenus - Clic cadenas → paywall | E31: Checkout | F31: 0.25 | G31: 19/06/2026
A32: Lot 1 | B32: Dashboard minimal placeholder | C32: Version simplifiée avec blocs disponibles en Lot 1 (placeholders pour parcours/stats qui viendront Lot 3). Liens vers cours/exos/TM/profil/paramètres. | D32: - Accessible après onboarding - Liens navigation principaux - Remplacé en Lot 3 | E32: Freemium | F32: 0.25 | G32: 19/06/2026 | H32: Remplacé au Lot 3
A33: Lot 1 | B33: Parrainage | C33: Génération code unique par user, dashboard parrainage, reward 10€ via Stripe Customer Balance, promo code -15% Stripe auto-attribué au filleul. | D33: - Code unique par user - Dashboard filleuls validés/en attente - Reward 10€ à validation - Promo -15% filleul | E33: Modèle abo | F33: 0.5 | G33: 19/06/2026 | H33: Reprise logique existante
A34: Lot 1 | B34: Écoles partenaires | C34: Matching automatique par domaine email à la vérification, application du crédit Stripe, notification user. | D34: - Matching auto à vérif email - Crédit Stripe appliqué - Notification user envoyée | E34: Auth + Stripe | F34: 0.5 | G34: 19/06/2026 | H34: Reprise logique existante
A35: Lot 1 | B35: Intégrations Brevo + Attio | C35: Brevo : templates emails transactionnels (bienvenue, vérif, reset, confirmation, rappel) via Symfony Mailer. Attio : commande app:attio:sync pour remonter users + abonnements. | D35: - Templates Brevo connectés - app:attio:sync fonctionnel - Emails transactionnels envoyés | E35: Auth + Checkout | F35: 0.5 | G35: 19/06/2026
A36: Lot 1 | B36: Recette fin de Lot 1 | C36: Tests E2E : visiteur → inscription → paywall → paiement → onboarding → dashboard → payant/freemium. Parrainage bout en bout. Corrections. | D36: - Tunnel monétisation E2E OK - Payant et freemium testés - Parrainage E2E - 0 anomalie critique | E36: Tous items Lot 1 | F36: 1 | G36: 19/06/2026
A37: Total lot 1 | C37: =SUM(F26:F36) -> 6.75
A38: LOT 2 — CŒUR D'APPRENTISSAGE + TAGEMAGE
A39: Lot 2 | B39: Création tickets backlog Lot 2 | C39: Découpage du Lot 2 en tickets détaillés. | D39: - Tous les items tracés en tickets - Critères d'acceptance rédigés | E39: Fin Lot 1 | F39: 1 | G39: 03/07/2026
A40: Lot 2 | B40: Bibliothèque de cours — catalogue | C40: Nav horizontale 6 sections TageMage + section Stratégie, accordéon chapitres, leçons dépliables, trait animé au scroll. Icônes + couleurs par section. | D40: - 6 sections + Stratégie affichées - Accordéon fonctionnel - Trait animé au scroll - Icônes + couleurs par section | E40: CRUD cours | F40: 0.5 | G40: 03/07/2026
A41: Lot 2 | B41: Page leçon complète | C41: Player Mux large, 4 onglets (Transcript / Notes éditables / Drill / Ask an Expert), panneau latéral sans cacher vidéo, like/dislike, navigation cours suivant/précédent, tracking 'leçon vue'. | D41: - Player Mux large format - 4 onglets fonctionnels - Notes éditables - Like/dislike - Navigation suivant/précédent - Tracking leçon vue | E41: Catalogue cours + Mux | F41: 1 | G41: 03/07/2026
A42: Lot 2 | B42: Drill | C42: 5 questions post-vidéo en format simple (5 réponses, correction texte, pas de vidéo). Pas dans les stats. CTA fin de vidéo 'Lance le drill'. Affichage modale ou section dédiée. | D42: - 5 Q post-vidéo - Pas comptabilisé dans stats - CTA fin de vidéo - Correction texte immédiate | E42: Page leçon + CRUD drills | F42: 1 | G42: 03/07/2026
A43: Lot 2 | B43: QuizInterface | C43: Composant central réutilisé (sous-tests, TageMage blanc, générateur, carnet). Header sticky + chrono + save localStorage (mécanique Tage blanc). Grille pastilles, question + 5 choix, flag, navigation, auto-submit à 0:00, warning questions vides, tracking temps par question. | D43: - Chrono décompte, rouge sous 60s - Save localStorage (ferme/réouvre = état restauré) - Pastilles couleur selon statut - Flag toggle - Auto-submit 0:00 - Tracking temps >1s | E43: Schema BDD + CRUD questions | F43: 2 | G43: 03/07/2026 | H43: Chemin critique
A44: Lot 2 | B44: Catalogue de sous-tests | C44: Nav 6 sections TageMage, toggle Généralistes/Thématiques, cards avec score/60 coloré, moyenne ASTPrep, boutons Lancer / Correction. | D44: - 6 sections + toggle G/T - Score/60 avec couleur - Moyenne ASTPrep affichée - Boutons fonctionnels | E44: CRUD exercices | F44: 0.75 | G44: 03/07/2026
A45: Lot 2 | B45: Cron calcul moyennes ASTPrep | C45: Commande app:compute:subtest-averages exécutée chaque nuit. Calcul de la moyenne des premiers passages par sous-test, filtré sur scores > 8/60 pour exclure les passages non sérieux. Stockage pour affichage sur les cards du catalogue. | D45: - Cron quotidien fonctionnel - Filtre scores > 8/60 appliqué - Premier passage user par sous-test uniquement - Moyennes affichées sur les cards catalogue sous-tests | E45: CRUD exercices + Catalogue sous-tests | F45: 0.25 | G45: 03/07/2026
A46: Lot 2 | B46: Mini-fenêtre debrief post-exo | C46: Après soumission : score grand format, 3 notions à travailler (thèmes les plus ratés), micro-feedback adaptatif (4 cas), bouton 'Afficher la correction'. | D46: - Score /60 ou /600 - 3 notions faibles identifiées - Feedback adapté au contexte - Bouton navigue vers correction | E46: QuizInterface | F46: 0.25 | G46: 03/07/2026
A47: Lot 2 | B47: CorrectionView | C47: Bandeau collapsible + pastilles vert/rouge. Par question : explication, vidéo Mux chargée à la demande (coût Mux), catégorisation erreur, flag. Bloc 'Pour progresser' en fin avec liens cours. Bouton entraînement pré-rempli. | D47: - Pastilles vert/rouge correct/incorrect - Vidéo chargée à la demande - Catégorisation erreur enregistrée - Bloc 'Pour progresser' avec liens - Bouton entraînement → générateur pré-rempli | E47: QuizInterface + CRUD catégories erreur | F47: 1 | G47: 03/07/2026
A48: Lot 2 | B48: Carnet d'erreurs V2 | C48: Layout 2 colonnes. Générateur spécifique carnet (chips compteur erreurs, 5/10/15 Q, chrono). Pie chart + métriques + info répétition espacée J+1/J+7. Liste complète avec suppression. Raisons erreurs affichées. | D48: - Chips compteur par sous-test/thème - Choix 5/10/15 Q - Option chrono - Correction immédiate - Pie chart + infos J+1/J+7 - Suppression individuelle/groupée | E48: CorrectionView | F48: 1.5 | G48: 03/07/2026
A49: Lot 2 | B49: Générateur d'entraînement | C49: Formulaire chips (sous-tests, thèmes, difficulté, durée). Résumé dynamique. Pré-remplissage URL (depuis correction ou stats). CTA disabled si 0 questions. Lance QuizInterface + CorrectionView. Pas de sauvegarde/stats. | D49: - Chips dynamiques - Résumé 'X questions disponibles' - Pré-remplissage URL fonctionne - CTA disabled si 0 Q - Boucle infinie correction → entraînement | E49: QuizInterface + CorrectionView | F49: 1 | G49: 03/07/2026 | H49: LA feature clé V3
A50: Lot 2 | B50: TageMage blanc — catalogue | C50: Grille 4 colonnes affichant les 20 TageMage classiques + 6 mensuels. Cards avec score/600 si passé ou badge 'Nouveau' sinon. Lien vers lancement. | D50: - 26 cards en grille - Score/600 si fait | E50: QuizInterface + CRUD TageMage | F50: 0.25 | G50: 03/07/2026 | H50: Réutilise QuizInterface
A51: Lot 2 | B51: TageMage blanc — orchestration examen | C51: Couche spécifique TageMage au-dessus de QuizRunner : création Exam + ExamAnswers, flow 6 steps successifs, écrans de pause (configurable env), timestamps par step, API POST JSON step-by-step pour enregistrement live, scoring complexe /600 (pondération aptitude verbale / résolution / logique). QuizRunner utilisé pour chaque step. | D51: - 6 steps enchaînés correctement - Pauses configurables affichées - Chaque step submit déclenche création d'ExamAnswers - Scoring /600 correct - Enregistrement live même si user crash - Pas de retour en arrière entre steps | E51: QuizInterface + CRUD TageMage | F51: 0.5 | G51: 03/07/2026
A52: Lot 2 | B52: TageMage blanc — résultats + partage | C52: Post-TM : chargement animé, score hero /600 + percentile, courbe en cloche, détail par sous-test vs moyenne, partage Discord. Entraînement post-TM → générateur avec thèmes faibles. | D52: - Chargement animé - Score hero + percentile - Courbe en cloche - 6 barres sous-test vs moyenne - Bouton partage Discord - Redirection entraînement avec pré-remplissage | E52: TageMage passage + générateur | F52: 0.5 | G52: 03/07/2026
A53: Lot 2 | B53: Recette fin de Lot 2 | C53: Tests E2E boucle complète : cours → drill → sous-test → debrief → correction → carnet → générateur. TageMage complet avec save localStorage testé (fermeture/réouverture). Corrections critiques et majeures. | D53: - Boucle complète fonctionnelle - Save localStorage validé sur fermeture/réouverture - 0 anomalie critique - 0 anomalie majeure | E53: Tous items Lot 2 | F53: 1.5 | G53: 03/07/2026 | H53: Lot le plus chargé
A54: Total lot 2 | C54: =SUM(F39:F53) -> 13
A55: LOT 3 — INTELLIGENCE & PROGRESSION
A56: Lot 3 | B56: Création tickets backlog Lot 3 | C56: Découpage du Lot 3 en tickets détaillés. | D56: - Tous les items tracés en tickets | E56: Fin Lot 2 | F56: 1 | G56: 17/07/2026
A57: Lot 3 | B57: Moteur de calcul du parcours | C57: Algo de génération : input = score visé + date examen + heures dispo. Calcul total heures selon tranche 25 pts (15 profils). Répartition items pondérés. Tranches 30min/1h/1,5h/2h/3h. Blocage si incohérence. Pas de 'bloquer date spécifique' (post-v1). | D57: - Calcul cohérent score visé / heures - 15 profils par tranche de 25 pts - Tranches simplifiées appliquées - Blocage avec message si incohérent - Régénération avec spinner | E57: CRUD parcours | F57: 1.5 | G57: 17/07/2026 | H57: Item le plus complexe
A58: Lot 3 | B58: Interface parcours adaptatif | C58: Bannière coaching (si heures < objectif). Toggle Liste/Calendrier. Barre progression globale. Vue Liste timeline. Vue Calendrier mensuel. Modale Personnaliser (slider + date picker). Points couleur activités. Items cliquables. | D58: - Bannière conditionnelle - Toggle switch les vues - Timeline et calendrier fonctionnels - Modale avec slider + date picker - Points couleur corrects - Items cliquables | E58: Moteur parcours | F58: 0.5 | G58: 17/07/2026
A59: Lot 3 | B59: Statistiques V2 | C59: Filtre temporel (7j/30j/90j/tout). 4 KPIs. Graphique 2 onglets. 7 Personal Best avec badge 'Nouveau'. Détail par thème (barres % + S'entraîner). Historique questions filtrable. Heatmap Strava 4-6 semaines. | D59: - Filtre temporel change l'état - 2 onglets graphique - 7 PB avec badge récent - Barres % triées croissant - 'S'entraîner' → générateur pré-rempli - Heatmap colorée | E59: Générateur + CorrectionView | F59: 1.5 | G59: 17/07/2026
A60: Lot 3 | B60: Dashboard bento complet | C60: Remplace placeholder Lot 1. Grille bento 4 colonnes. Cards : courbe TM blancs, score estimé + FAQ, temps semaine, programme du jour, cours live, streak + Top X%, erreurs à réviser. Affiche le popup défi du jour (mécanique développée en Lot 5) | D60: - Cards visibles sans scroll 1440x900 - Popup défi 1x/jour (localStorage) - Tooltip score - Clics navigation - Graphiques Chart.js fonctionnels - Intègre les widgets gamification (streak, PB, heatmap) développés au Lot 5" | E60: Stats + Parcours | F60: 0.5 | G60: 17/07/2026
A61: Lot 3 | B61: Recette fin de Lot 3 | C61: Tests E2E : onboarding → parcours généré → dashboard peuplé → stats remontent données Lot 2. Cohérence chiffres entre carnet/stats/dashboard. Corrections. | D61: - Parcours généré selon inputs - Dashboard peuplé correctement - Cohérence chiffres validée - 0 anomalie critique | E61: Tous items Lot 3 | F61: 1 | G61: 17/07/2026
A62: Total lot 3 | C62: =SUM(F56:F61) -> 6
A63: LOT 4 — OUTILS & COMMUNAUTÉ
A64: Lot 4 | B64: Création tickets backlog Lot 4 | C64: Découpage du Lot 4 en tickets détaillés. | D64: - Tous les items tracés en tickets | E64: Fin Lot 3 | F64: 1 | G64: 24/07/2026
A65: Lot 4 | B65: Flashcards | C65: Configurateur chips (sous-test, thèmes, statut, nombre, chrono). Carte flip 3D. 3 boutons Anki ('Je savais' / 'J'hésitais' / 'Je ne savais pas'). Message prochaine révision 1s. Progression affichée. | D65: - Chips sous-test avec icônes - Thèmes dynamiques - Carte flip 3D - 3 boutons évaluation - Message révision 1s | E65: CRUD flashcards | F65: 1 | G65: 24/07/2026
A66: Lot 4 | B66: Calcul mental | C66: Chips config (opération, difficulté, durée). Session chrono. Input auto-focus + re-focus. Flash vert/rouge. Timer pause onglet inactif. Record localStorage. Classement session côté client. | D66: - Opérations selon difficulté - Timer pause onglet inactif - Input auto-focus + re-focus - Flash vert/rouge - Classement filtré côté client - Record localStorage | E66: — | F66: 0.75 | G66: 24/07/2026
A67: Lot 4 | B67: Lecture alphabétique | C67: Chips config (lettres, durée). Session chrono, affichage lettre + input position (1-26). Classement. | D67: - Chips config - Session chrono - Input position 1-26 - Classement | E67: — | F67: 0.5 | G67: 24/07/2026
A68: Lot 4 | B68: Fiches PDF | C68: Catalogue de fiches récap téléchargeables (formules, tables, astuces). Nav 6 sections, cards avec download. | D68: - 6 sections navigables - Cards avec bouton download - Fiches stockées en admin | E68: — | F68: 0.25 | G68: 24/07/2026
A69: Lot 4 | B69: Cours Live dashboard + sync events Discord | C69: Card cours du soir sur dashboard : sujet + lien Discord + calendrier + replays YouTube. Sync events Discord auto via API Discord pour lives planifiés. | D69: - Card live avec bonnes infos - Bouton rejoindre ouvre Discord - Replays YouTube listés - Cron sync events Discord | E69: Dashboard bento | F69: 0.25 | G69: 24/07/2026
A70: Lot 4 | B70: Classement défis | C70: Podium 3 meilleurs + tableau top 20. Onglets mensuel/trimestriel. Filtrage par pseudo. Mis à jour via cron quotidien. | D70: - Podium 3 meilleurs - Tableau top 20 - Onglets mensuel/trimestriel - Cron mise à jour | E70: QuizInterface + Stats | F70: 0.75 | G70: 24/07/2026
A71: Lot 4 | B71: Recette fin de Lot 4 | C71: Tests outils (flashcards, calcul, lecture), PDF téléchargeables, cours live, classement. Corrections. | D71: - Outils fonctionnels - PDF téléchargeables - Cours live remonté - Classement fonctionnel - 0 anomalie critique | E71: Tous items Lot 4 | F71: 1 | G71: 24/07/2026
A72: Total lot 4 | C72: =SUM(F64:F71) -> 5.5
A73: LOT 5 — GAMIFICATION & FINITION
A74: Lot 5 | B74: Création tickets backlog Lot 5 | C74: Découpage du Lot 5 en tickets détaillés. | D74: - Tous les items tracés en tickets | E74: Fin Lot 4 | F74: 1 | G74: 31/07/2026
A75: Lot 5 | B75: Gamification complète | C75: Développement de la mécanique gamification (les widgets eux-mêmes sont déjà affichés au Dashboard Lot 3 et Stats Lot 3, ici on ajoute les animations et triggers) : calcul streak + Top X%, détection 7 Personal Best + badge 'Nouveau' si récent, animation PB conditionnelle (compteur 1.5s + confettis 2s), popup défi du jour 1x/jour, ~20 mini pop-ups contextuels, célébrations post-session, logique bannière coaching progressive, heatmap (coloration selon activité). | D75: - Streak Top X% - 7 PB avec badge Nouveau - Animation PB conditionnelle - Popup défi 1x/jour - Pop-ups contextuels - Heatmap colorée - Partage Discord présent | E75: Stats + Dashboard + TM | F75: 1.5 | G75: 31/07/2026 | H75: Widgets affichés en Lot 3 (dashboard + stats). Lot 5 = mécanique + animations. Partage Discord TM déjà dans Lot 2
A76: Lot 5 | B76: Notifications user | C76: Page liste complète + dropdown dashboard. 5 types (classique, module, rappel, achievement, urgent). Marquage lu/non lu. | D76: - Page liste fonctionnelle - Dropdown dashboard - 5 types - Marquage lu/non lu persisté | E76: Dashboard bento | F76: 0.5 | G76: 31/07/2026
A77: Lot 5 | B77: Paramètres user + FAQ score | C77: Page paramètres : profil, dark mode toggle (optionnel), toggles notifications, tiers temps, facturation Stripe (redirect portal). FAQ explication calcul score. | D77: - Profil éditable - Toggles notifications - Redirection portal Stripe - FAQ score texte clair | E77: Auth + Stripe | F77: 0.5 | G77: 31/07/2026
A78: Lot 5 | B78: Recette fin de Lot 5 | C78: Audit visuel global, tests de la gamification, notifications, paramètres. Corrections. | D78: - Gamification testée bout en bout - Notifications fonctionnelles - Paramètres OK - 0 anomalie critique | E78: Tous items Lot 5 | F78: 0.5 | G78: 31/07/2026
A79: Total lot 5 | C79: =SUM(F74:F78) -> 4
A80: LOT 6 — MIGRATION & GO-LIVE
A81: Lot 6 | B81: Création tickets backlog Lot 6 | C81: Découpage du Lot 6 en tickets détaillés. | D81: - Tous les items tracés en tickets | E81: Fin Lot 5 | F81: 1 | G81: 07/08/2026
A82: Lot 6 | B82: Script migration cours + exercices + questions | C82: Basé sur étude migration Lot 0. Script SQL ou commande Symfony. Migration catégories, sous-catégories, cours, vidéos Mux, exercices, questions, drills si compatibles. Dry run staging puis prod. | D82: - Script migration fonctionnel - Dry run staging sans erreur - Migration prod réussie - Vérifications post-migration OK | E82: Étude migration Lot 0 | F82: 2 | G82: 07/08/2026 | H82: Conditionne contenu V3
A83: Lot 6 | B83: Migration users | C83: Selon décision fin Lot 5. Si migration : users (2400), abonnements Stripe avec ré-association nouveau modèle, historiques scores, carnet erreurs, liaisons Discord, parcours en cours. | D83: - Users migrés avec abos - Historiques scores préservés - Carnet erreurs migré - Liaisons Discord conservées | E83: Script migration cours + Modèle abo | F83: 1.5 | G83: 07/08/2026 | H83: Décision fin Lot 5
A84: Lot 6 | B84: Sync intégrations + crons | C84: Attio, Brevo, Sentry projet V3, Cronitor, LogRocket. Commandes cron : app:subscription:daily, app:checking:discord, app:attio:sync, app:check-pending-discord-channels. | D84: - Tous flux intégrations testés - 4 crons actifs - Monitoring Cronitor OK | E84: Tous Lots | F84: 1 | G84: 07/08/2026
A85: Lot 6 | B85: Recette finale + soft launch + go-live | C85: Tests E2E bout en bout sur parcours complet (inscription → onboarding → dashboard → cours → exo → correction → TageMage → stats → parcours). 0 anomalie critique/majeure. Soft launch cohorte 50-100 users. Corrections. Go-live. | D85: - Parcours complet fonctionnel - 0 anomalie critique - 0 anomalie majeure - Performance <3s chargement - Soft launch validé - Go-live | E85: Tous Lots | F85: 3 | G85: 07/08/2026
A86: Total lot 6 | C86: =SUM(F81:F85) -> 8.5
A87: SOUS-TOTAL | F87: =SUM(F2:F85) -> 63.25
A88: BUFFER 10% | F88: =ROUND(F87*0.1,2) -> 6.33
A89: TOTAL V1 AVEC BUFFER | F89: =F87+F88 -> 69.58

Sheet Vue par lot
A1: Lot | B1: Nom | C1: Nb items | D1: Durée (j) | E1: Durée (sem) | F1: Fin prévue | G1: Features critiques | H1: Condition de sortie
A2: Lot 0 | B2: Fondations | C2: =IFERROR(__xludf.DUMMYFUNCTION("COUNTUNIQUE(Roadmap!B3:B23)"),21.0) -> 21 | D2: =Roadmap!C24 -> 19.5 | E2: 3.6 | F2: 05/06/2026 | G2: Setup + BDD + Auth + Abonnements + Admin complet | H2: Grégoire peut saisir du contenu, user test peut s'inscrire
A3: Lot 1 | B3: Monétisation & entrée | C3: =IFERROR(__xludf.DUMMYFUNCTION("COUNTUNIQUE(Roadmap!B26:B36)"),11.0) -> 11 | D3: =Roadmap!C37 -> 6.75 | E3: 1.4 | F3: 19/06/2026 | G3: Onboarding + Stripe + Freemium + Parrainage + Écoles + Discord sync | H3: Tunnel visiteur → payant → onboardé E2E
A4: Lot 2 | B4: Cœur + TageMage | C4: =IFERROR(__xludf.DUMMYFUNCTION("COUNTUNIQUE(Roadmap!B39:B53)"),15.0) -> 15 | D4: =Roadmap!C54 -> 13 | E4: 2.7 | F4: 03/07/2026 | G4: QuizInterface + CorrectionView + Carnet + Générateur + TageMage blanc | H4: Boucle cours→drill→exo→correction→entraînement ciblé
A5: Lot 3 | B5: Intelligence & progression | C5: =IFERROR(__xludf.DUMMYFUNCTION("COUNTUNIQUE(Roadmap!B56:B61)"),6.0) -> 6 | D5: =Roadmap!C62 -> 6 | E5: 1.2 | F5: 17/07/2026 | G5: Parcours adaptatif + Stats V2 + Dashboard bento | H5: Marie voit sa prochaine action et sa progression
A6: Lot 4 | B6: Outils & communauté | C6: =IFERROR(__xludf.DUMMYFUNCTION("COUNTUNIQUE(Roadmap!B64:B71)"),8.0) -> 8 | D6: =Roadmap!C72 -> 5.5 | E6: 1.2 | F6: 24/07/2026 | G6: Flashcards + Calcul mental + Lecture alpha + PDF + Discord | H6: Outils périphériques + interaction communautaire
A7: Lot 5 | B7: Gamification & finition | C7: =IFERROR(__xludf.DUMMYFUNCTION("COUNTUNIQUE(Roadmap!B74:B78)"),5.0) -> 5 | D7: =Roadmap!C79 -> 4 | E7: 0.7 | F7: 31/07/2026 | G7: Célébrations + Notifications + Paramètres + FAQ | H7: Effet WOW + récap expérience utilisateur
A8: Lot 6 | B8: Migration & go-live | C8: =IFERROR(__xludf.DUMMYFUNCTION("COUNTUNIQUE(Roadmap!B81:B85)"),5.0) -> 5 | D8: =Roadmap!C86 -> 8.5 | E8: 1.7 | F8: 07/08/2026 | G8: Scripts migration + Sync intégrations + Recette finale | H8: 0 anomalie critique/majeure, go-live
A9: TOTAL | C9: =SUM(C2:C8) -> 71 | D9: =SUM(D2:D8) -> 63.25 | E9: =SUM(E2:E8) -> 12.5
A10: BUFFER 10% | D10: =ROUND(D9*0.1,2) -> 6.33 | E10: =ROUND(D10/5,1) -> 1.3
A11: TOTAL V1 AVEC BUFFER | D11: =D9+D10 -> 69.58 | E11: =ROUND(D11/5,1) -> 13.9

Sheet Options
A1: Option | B1: Nom | C1: Description | D1: Durée (j) | E1: Condition d'activation | F1: Décision à prendre
A2: Option A | B2: API mobile | C2: Endpoints auth (Bearer), /api/flashcards, /api/calcul-mental, /api/lecture-alphabetique, /api/courses avec Mux signé, /api/completions sauvegarde vue de cours. Documentation OpenAPI + environnement test dev mobile. Scope : cours + flashcards + calcul + lecture (pas exos/sous-tests/TM). | D2: 3 | E2: Choix de faire l'app native (dev séparé) | F2: Fin Lot 4 / début Lot 5
A3: Option A | B3: App Mobile | C3: App mobile basique pour les mini jeux, la consultation des cours | D3: 5~10 | E3: Choix de faire l'app native (dev séparé) | F3: Fin Lot 4 / début Lot 5
A4: Option B | B4: PWA complète | C4: Manifest + service worker avancé. Cache management (cours cache-first, sous-tests network-first, carnet background-sync). Mode offline consultation. Splash screen. Installable iOS Safari + Android Chrome. Lighthouse PWA > 90. | D4: 5 | E4: Choix de la PWA comme solution mobile | F4: Fin Lot 4 / début Lot 5
A5: ⚠️ Options exclusives : on active l'une OU l'autre, pas les deux.

Sheet Timeline
A1: Semaine | B1: Dates | C1: Lot en cours | D1: Jalons / Livrables
A2: S1 | B2: 11/05 → 15/05 | C2: Lot 0 — Fondations
A3: S2 | B3: 18/05 → 22/05 | C3: Lot 0 — Fondations
A4: S3 | B4: 25/05 → 29/05 | C4: Lot 0 — Fondations
A5: S4 | B5: 01/06 → 05/06 | C5: Lot 0 — Fondations | D5: ✓ Fin Lot 0 — Recette + livraison
A6: S5 | B6: 08/06 → 12/06 | C6: Lot 1 — Monétisation | D6: ✓ Fin Lot 1 — Recette + livraison
A7: S6 | B7: 15/06 → 19/06 | C7: Lot 2 — Cœur + TM
A8: S7 | B8: 22/06 → 26/06 | C8: Lot 2 — Cœur + TM
A9: S8 | B9: 29/06 → 03/07 | C9: Lot 2 — Cœur + TM | D9: ✓ Fin Lot 2 — Recette + livraison
A10: S9 | B10: 06/07 → 10/07 | C10: Lot 3 — Intelligence | D10: ✓ Fin Lot 3 — Recette + livraison
A11: S10 | B11: 13/07 → 17/07 | C11: Lot 4 — Outils
A12: S11 | B12: 20/07 → 24/07 | C12: Lot 4 — Outils | D12: ✓ Fin Lot 4 — Recette + livraison
A13: S12 | B13: 27/07 → 31/07 | C13: Lot 6 — Migration
A14: S13 | B14: 03/08 → 07/08 | C14: Lot 6 — Migration | D14: ✓ Fin Lot 6 — Recette + livraison
A15: S14 | B15: 10/08 → 14/08 | C15: Buffer / marge | D15: Tampon global 10%

Sheet Contenu Grégoire
A1: Livrable | B1: Description | C1: Quantité | D1: Deadline | E1: Lot utilisateur | F1: Notes
A2: Micro-compétences + capsules vidéo | B2: Découpage du TageMage en 100 micro-compétences. Enregistrement des capsules vidéo courtes. | C2: ~100 | D2: 05/06/2026 | E2: Lot 2 | F2: Saisie admin dispo fin Lot 0
A3: Test de positionnement | B3: 12-15 questions mappées aux micro-compétences. Scoring par domaine. | C3: 12-15 Q | D3: 05/06/2026 | E3: Lot 1
A4: Drills par leçon | B4: 5 questions simples post-vidéo par leçon pour valider la compréhension immédiate. | C4: ~500 Q (100 leçons × 5) | D4: 05/06/2026 | E4: Lot 2 | F4: Pas de correction vidéo nécessaire
A5: 15 profils de parcours | B5: Découpage des items pondérés en heures par tranche de 25 points de score. Total d'heures à faire par profil. | C5: 15 profils | D5: 03/07/2026 | E5: Lot 3 | F5: Dépend des items créés au Lot 2
A6: Catégorisations d'erreur | B6: Liste des raisons d'erreur à proposer à l'élève (manque de temps, mauvaise lecture, etc.). | C6: ~8-10 catégories | D6: 19/06/2026 | E6: Lot 2
A7: Moyennes ASTPrep par sous-test | B7: Calcul des moyennes historiques par sous-test pour affichage sur les cards catalogue. | C7: 6 moyennes | D7: 19/06/2026 | E7: Lot 2 | F7: Données extraites de la prod actuelle
A8: Corrections vidéo questions | B8: Vidéos de correction par question d'exercice (existant + nouveau contenu). | C8: Variable | D8: 03/07/2026 | E8: Lot 2 | F8: Chargement à la demande pour coût Mux
A9: Fiches PDF récap | B9: Fiches téléchargeables (formules, tables, astuces CM, etc.). | C9: ~20-30 fiches | D9: 17/07/2026 | E9: Lot 4
